langchain_callback_parquet_logger/__init__.py
langchain_callback_parquet_logger/background_retrieval.py
langchain_callback_parquet_logger/batch.py
langchain_callback_parquet_logger/config.py
langchain_callback_parquet_logger/logger.py
langchain_callback_parquet_logger/storage.py
langchain_callback_parquet_logger/tagging.py
langchain_callback_parquet_logger-2.0.3.dist-info/licenses/LICENSE
langchain_callback_parquet_logger-2.0.3.dist-info/METADATA
langchain_callback_parquet_logger-2.0.3.dist-info/WHEEL
langchain_callback_parquet_logger-2.0.3.dist-info/top_level.txt
langchain_callback_parquet_logger-2.0.3.dist-info/RECORD
