Metadata-Version: 2.4
Name: langchain-callback-parquet-logger
Version: 2.0.3
Summary: A Parquet-based callback handler for logging LangChain LLM interactions
Author-email: turbo3136 <turbo3136@gmail.com>
License: MIT
Project-URL: Homepage, https://github.com/turbo3136/langchain-callback-parquet-logger
Project-URL: Repository, https://github.com/turbo3136/langchain-callback-parquet-logger
Project-URL: Issues, https://github.com/turbo3136/langchain-callback-parquet-logger/issues
Keywords: langchain,logging,parquet,llm,callback,monitoring
Classifier: Development Status :: 4 - Beta
Classifier: Intended Audience :: Developers
Classifier: License :: OSI Approved :: MIT License
Classifier: Programming Language :: Python :: 3
Classifier: Programming Language :: Python :: 3.8
Classifier: Programming Language :: Python :: 3.9
Classifier: Programming Language :: Python :: 3.10
Classifier: Programming Language :: Python :: 3.11
Classifier: Programming Language :: Python :: 3.12
Classifier: Topic :: Software Development :: Libraries :: Python Modules
Classifier: Topic :: System :: Logging
Requires-Python: >=3.8
License-File: LICENSE
Requires-Dist: pyarrow>=10.0.0
Requires-Dist: langchain-core>=0.1.0
Requires-Dist: pandas>=1.3.0
Provides-Extra: test
Requires-Dist: pytest>=7.0.0; extra == "test"
Requires-Dist: pytest-asyncio>=0.21.0; extra == "test"
Requires-Dist: pytest-mock>=3.10.0; extra == "test"
Requires-Dist: pandas>=1.3.0; extra == "test"
Provides-Extra: background
Requires-Dist: openai>=1.0.0; extra == "background"
Requires-Dist: pandas>=1.3.0; extra == "background"
Requires-Dist: tqdm>=4.60.0; extra == "background"
Provides-Extra: s3
Requires-Dist: boto3>=1.26.0; extra == "s3"
Dynamic: license-file
